cdbc/__init__.py
cdbc/cache.py
cdbc/message.py
cdbc/postgresql.py
cdbc-0.0.15.dist-info/METADATA
cdbc-0.0.15.dist-info/WHEEL
cdbc-0.0.15.dist-info/top_level.txt
cdbc-0.0.15.dist-info/RECORD
